README.md
setup.py
stagesep/__init__.py
stagesep/config.py
stagesep/core.py
stagesep/ocr.py
stagesep/utils.py
stagesep.egg-info/PKG-INFO
stagesep.egg-info/SOURCES.txt
stagesep.egg-info/dependency_links.txt
stagesep.egg-info/requires.txt
stagesep.egg-info/top_level.txt