Metadata-Version: 1.0
Name: stagesep
Version: 0.1.0
Summary: detect stages in video
Home-page: https://github.com/williamfzc/stagesep
Author: williamfzc
Author-email: fengzc@vip.qq.com
License: UNKNOWN
Platform: UNKNOWN
